verilog/vending_machine.v
`timescale 1ns/1ps

module VendingMachine(
    input clk,
    input rst,
    input [2:0] coin,      // 3-bit output to represent coin denominations (001, 010, 011, 100)
    input [2:0] item,      // 3-bit output to represent item (001, 010, 011, 100, 101, 110)
    input cancel,          // 1-bit input to represent cancel transaction
    output reg [2:0] dispense,  // 3-bit output to represent dispensing item (001, 010, 011, 100, 101, 110)
    output reg [4:0] change,    // 5-bit output to represent returning change (0 to 31 Rs)
    output reg [1:0] state,     // 2-bit output to represent the current state
    output reg [4:0] total      // 5-bit output to represent the total amount inserted (0 to 31 Rs)
);

// State definitions
localparam ACCEPT  = 2'b00;
localparam DISPENSE= 2'b01;
localparam CANCEL  = 2'b10;

// Coin values
localparam [2:0] RS1 = 3'b001;
localparam [2:0] RS2 = 3'b010;
localparam [2:0] RS5 = 3'b011;
localparam [2:0] RS10 = 3'b100;

//Item Definition
localparam [2:0] TOFFEE = 3'b001;
localparam [2:0] CHOCOLATE = 3'b010;
localparam [2:0] BISCUITS = 3'b011;
localparam [2:0] CHIPS = 3'b100;
localparam [2:0] JUICE = 3'b101;
localparam [2:0] COLD_DRINK = 3'b110;


// Item prices
localparam TOFFEE_PRICE = 2;         // Rs2
localparam CHOCOLATE_PRICE = 5;     // Rs5
localparam BISCUITS_PRICE = 10;     // Rs10
localparam CHIPS_PRICE = 10;
localparam JUICE_PRICE = 20;
localparam COLD_DRINK_PRICE = 20;


always @(posedge clk or posedge rst) begin
    if (rst) begin
        state <= ACCEPT;
        total <= 0;
        dispense <= 3'b000;
        change <= 0;
    end else begin
        case (state)
            ACCEPT: begin
                change <= 0;
                if (cancel) begin
                    state <= CANCEL;
                    $display("Item was cancelled");
                end 
                else if (coin) begin
                    if (coin == RS1)
                        total <= total + 1;
                    else if (coin == RS2)
                        total <= total + 2;
                    else if (coin == RS5)
                        total <= total + 5;
                    else if (coin == RS10)
                        total <= total + 10;
                end
                if (item == TOFFEE && total >= TOFFEE_PRICE) begin
                        state <= DISPENSE;
                        dispense <= TOFFEE;
                        $display("TOFFEE successfully dispensed");
                    end else if (item == CHOCOLATE && total >= CHOCOLATE_PRICE) begin
                        state <= DISPENSE;
                        dispense <= CHOCOLATE;
                        $display("CHOCOLATE successfully");
                    end else if (item == BISCUITS && total >= BISCUITS_PRICE) begin
                        state <= DISPENSE;
                        dispense <= BISCUITS;
                        $display("BISCUITS successfully dispensed");
                        state <= ACCEPT;
                    end else if (item == CHIPS && total >= CHIPS_PRICE) begin
                        state <= DISPENSE;
                        dispense <= CHIPS;
                        $display("CHIPS successfully dispensed");
                    end else if (item == JUICE && total >= JUICE_PRICE) begin
                        state <= DISPENSE;
                        dispense <= JUICE;
                        $display("JUICE successfully dispensed");
                    end else if (item == COLD_DRINK && total >= COLD_DRINK_PRICE) begin
                        state <= DISPENSE;
                        dispense <= COLD_DRINK;
                        $display("COLD_DRINK successfully dispensed");
                    end
            end
            
            DISPENSE: begin
                if (dispense == TOFFEE) begin
                    change <= total - TOFFEE_PRICE;
                    dispense <= 3'b000;
                end else if (dispense == CHOCOLATE) begin
                    change <= total - CHOCOLATE_PRICE;
                    dispense <= 3'b000;
                end else if (dispense == BISCUITS) begin
                    change <= total - BISCUITS_PRICE;
                    dispense <= 3'b000;
                end else if (dispense == CHIPS) begin
                    change <= total - CHIPS_PRICE;
                    dispense <= 3'b000;
                end else if (dispense == JUICE) begin
                    change <= total - JUICE_PRICE;
                    dispense <= 3'b000;
                end else if (dispense == COLD_DRINK) begin
                    change <= total - COLD_DRINK_PRICE;
                    dispense <= 3'b000;
                end
                state <= ACCEPT;
                total <= 0;
                end
            CANCEL: begin
                change <= total;
                state <= ACCEPT;
                total <= 0;
                dispense <= 0;
            end
            default: begin
                state <= ACCEPT;
                total <= 0;
                dispense <= 0;
                change <= 0;
            end
        endcase
    end
end
endmodule

verilog/vending_machine_tb.v
`timescale 1ns/1ps

module VendingMachine_tb;
    reg clk;
    reg rst;
    reg [2:0] coin;
    reg [2:0] item;
    reg cancel;
    wire [2:0] dispense;
    wire [4:0] change;
    wire [1:0] state;
    wire [4:0] total;

    VendingMachine uut (
        .clk(clk),
        .rst(rst),
        .coin(coin),
        .item(item),
        .cancel(cancel),
        .dispense(dispense),
        .change(change),
        .state(state),
        .total(total)
    );

    // Coin values
    localparam [2:0] RS1 = 3'b001;
    localparam [2:0] RS2 = 3'b010;
    localparam [2:0] RS5 = 3'b011;
    localparam [2:0] RS10 = 3'b100;

    //Item Definition
    localparam [2:0] TOFFEE = 3'b001;
    localparam [2:0] CHOCOLATE = 3'b010;
    localparam [2:0] BISCUITS = 3'b011;
    localparam [2:0] CHIPS = 3'b100;
    localparam [2:0] JUICE = 3'b101;
    localparam [2:0] COLD_DRINK = 3'b110;

    // Clock generation
    always #5 clk = ~clk;  // 10ns clock period (100MHz)

    // Test sequence
    initial begin
        $dumpfile("ven_waveform.vcd");
        $dumpvars(1);
        // Initialize inputs
        clk = 1;
        rst = 1;
        coin = 0;
        item = 0;
        cancel = 0;

        // Reset the system
        #20 rst = 0;

        // Test case 1
        #10 item = TOFFEE;  // Select item 1 (Rs5)
        #10 coin = RS10;  // Rs1
        #10 coin = 0;  // Stop inserting coins
        #30
        // Test case 2
        #10 item = CHOCOLATE;  // Select item 1 (Rs5)
        #10 coin = RS2;  // Rs1
        #10 coin = RS2;  // Rs1
        #10 coin = RS2;  // Rs1
        #10 coin = 0;  // Stop inserting coins
        #30
        // Test case 3
        #10 item = CHIPS;  // Select item 1 (Rs5)
        #10 coin = RS5;  // Rs1
        #10 coin = RS5;  // Rs1
        #10 coin = 0;  // Stop inserting coins
        #30
        // Test case 4
        #10 item = JUICE;  // Select item 1 (Rs5)
        #10 coin = RS10;  // Rs1
        #10 coin = RS5;  // Rs1
        #10 coin = 0; cancel = 1;
        #10 cancel = 0;
        #50 $finish();  // End simulation
    end
endmodule

verilog/ven_waveform.vcd
$date
	Tue Jul 16 18:49:49 2024
$end
$version
	Icarus Verilog
$end
$timescale
	1ps
$end
$scope module VendingMachine_tb $end
$var wire 5 ! total [4:0] $end
$var wire 2 " state [1:0] $end
$var wire 3 # dispense [2:0] $end
$var wire 5 $ change [4:0] $end
$var parameter 3 % BISCUITS $end
$var parameter 3 & CHIPS $end
$var parameter 3 ' CHOCOLATE $end
$var parameter 3 ( COLD_DRINK $end
$var parameter 3 ) JUICE $end
$var parameter 3 * RS1 $end
$var parameter 3 + RS10 $end
$var parameter 3 , RS2 $end
$var parameter 3 - RS5 $end
$var parameter 3 . TOFFEE $end
$var reg 1 / cancel $end
$var reg 1 0 clk $end
$var reg 3 1 coin [2:0] $end
$var reg 3 2 item [2:0] $end
$var reg 1 3 rst $end
$upscope $end
$enddefinitions $end
$comment Show the parameter values. $end
$dumpall
b1 .
b11 -
b10 ,
b100 +
b1 *
b101 )
b110 (
b10 '
b100 &
b11 %
$end
#0
$dumpvars
13
b0 2
b0 1
10
0/
b0 $
b0 #
b0 "
b0 !
$end
#5000
00
#10000
10
#15000
00
#20000
10
03
#25000
00
#30000
10
b1 2
#35000
00
#40000
b1010 !
10
b100 1
#45000
00
#50000
b1 #
b1 "
10
b0 1
#55000
00
#60000
b0 !
b0 "
b0 #
b1000 $
10
#65000
00
#70000
b0 $
10
#75000
00
#80000
10
#85000
00
#90000
10
b10 2
#95000
00
#100000
b10 !
10
b10 1
#105000
00
#110000
b100 !
10
#115000
00
#120000
b110 !
10
#125000
00
#130000
b10 #
b1 "
10
b0 1
#135000
00
#140000
b0 !
b0 "
b0 #
b1 $
10
#145000
00
#150000
b0 $
10
#155000
00
#160000
10
#165000
00
#170000
10
b100 2
#175000
00
#180000
b101 !
10
b11 1
#185000
00
#190000
b1010 !
10
#195000
00
#200000
b100 #
b1 "
10
b0 1
#205000
00
#210000
b0 !
b0 "
b0 #
10
#215000
00
#220000
10
#225000
00
#230000
10
#235000
00
#240000
10
b101 2
#245000
00
#250000
b1010 !
10
b100 1
#255000
00
#260000
b1111 !
10
b11 1
#265000
00
#270000
b10 "
10
1/
b0 1
#275000
00
#280000
b0 !
b0 "
b1111 $
10
0/
#285000
00
#290000
b0 $
10
